multimerge.cpython-39-darwin.so
multimerge-0.2.0.dist-info/RECORD
multimerge-0.2.0.dist-info/LICENSE
multimerge-0.2.0.dist-info/WHEEL
multimerge-0.2.0.dist-info/top_level.txt
multimerge-0.2.0.dist-info/METADATA
