Metadata-Version: 2.1
Name: multimerge
Version: 0.2.0
Summary: a k-way merge algorithm to replace heapq.merge
Author: Dennis Sweeney
Author-email: Dennis Sweeney <sweeney.427@osu.edu>
Project-URL: Homepage, https://github.com/sweeneyde/multimerge
Project-URL: Bug Tracker, https://github.com/sweeneyde/multimerge
Classifier: Programming Language :: Python :: 3
Classifier: License :: OSI Approved :: MIT License
Classifier: Operating System :: OS Independent
Requires-Python: >=3.9
License-File: LICENSE
